{"city_id":3064,"id":"helsinki-finland","latitude":"60.171075","longitude":"24.932478","name":"Helsinki, Finland","type":"landing_point","cables":[{"cable_id":1609,"id":"bcs-north---phase-1","name":"BCS North - Phase 1","is_tbd":"false"},{"cable_id":1610,"id":"bcs-north---phase-2","name":"BCS North - Phase 2","is_tbd":"false"},{"cable_id":1624,"id":"baltic-sea-submarine-cable","name":"Baltic Sea Submarine Cable","is_tbd":"false"},{"cable_id":1816,"id":"c-lion1","name":"C-Lion1","is_tbd":"false"},{"cable_id":1710,"id":"eastern-light","name":"Eastern Light","is_tbd":"false"},{"cable_id":1242,"id":"finland-estonia-connection-fec","name":"Finland Estonia Connection (FEC)","is_tbd":"false"},{"cable_id":1263,"id":"finland-estonia-2-eesf-2","name":"Finland-Estonia 2 (EESF-2)","is_tbd":"false"},{"cable_id":1268,"id":"finland-estonia-3-eesf-3","name":"Finland-Estonia 3 (EESF-3)","is_tbd":"false"}],"is_tbd":"false"}
