{"type":"cable","rfs":"Q4 2014","length":"2,500 km","owners":"SEACOM","description":"[{\"longitude\":\"27.866667\",\"name\":\"East London, South Africa\",\"latitude\":\"-32.983281\",\"id\":\"9248\"},{\"longitude\":\"31.757858\",\"name\":\"Mtunzini, South Africa\",\"latitude\":\"-28.950645\",\"id\":\"5942\"},{\"longitude\":\"25.569918\",\"name\":\"Port Elizabeth, South Africa\",\"latitude\":\"-33.932638\",\"id\":\"8847\"},{\"longitude\":\"18.155554\",\"name\":\"Yzerfontein, South Africa\",\"latitude\":\"-33.348187\",\"id\":\"9844\"}]","url":"n.a.","notes":null,"name":"South Atlantic Marine System (SAMS)","id":"1773"}
