{"id":"esat-1","name":"ESAT-1","cable_id":1223,"landing_points":[{"landing_point_id":5863,"id":"kilmore-quay-ireland","name":"Kilmore Quay, Ireland","latlon":"52.174585,-6.584101","url":"#/landing-point/kilmore-quay-ireland","is_tbd":"false"},{"landing_point_id":5742,"id":"sennen-cove-united-kingdom","name":"Sennen Cove, United Kingdom","latlon":"50.076057,-5.698750","url":"#/landing-point/sennen-cove-united-kingdom","is_tbd":"false"}],"length":"261 km","rfs":"1999 August","owners":"Esat BT","url":"http://www.fiberatlantic.com/system/J6QpP","notes":null}
