{"id":"grace-hopper","name":"Grace Hopper","cable_id":2112,"landing_points":[{"landing_point_id":5767,"id":"bellport-ny-united-states","name":"Bellport, NY, United States","latlon":"40.755544,-72.937813","url":"#/landing-point/bellport-ny-united-states"},{"landing_point_id":3067,"id":"bilbao-spain","name":"Bilbao, Spain","latlon":"43.268348,-2.946159","url":"#/landing-point/bilbao-spain"},{"landing_point_id":4554,"id":"bude-united-kingdom","name":"Bude, United Kingdom","latlon":"50.828208,-4.544401","url":"#/landing-point/bude-united-kingdom"}],"length":"n.a.","rfs":"2022","owners":"Google","url":"https://cloud.google.com","notes":null}
