{"cables":[{"name":"Russian Optical Trans-Arctic Cable System (ROTACS)","cable_id":1244,"id":"russian-optical-trans-arctic-cable-system-rotacs"},{"name":"South Atlantic Express (SAEx)","cable_id":1669,"id":"south-atlantic-express-saex"},{"name":"Australia-Singapore Cable (ASC)","cable_id":1683,"id":"australia-singapore-cable-asc"},{"name":"WASACE Europe","cable_id":1707,"id":"wasace-europe"},{"name":"EUROPA","cable_id":1708,"id":"europa"},{"name":"Arctic Fibre","cable_id":1712,"id":"arctic-fibre"},{"name":"WASACE Africa","cable_id":1721,"id":"wasace-africa"},{"name":"Seabras-1","cable_id":1728,"id":"seabras-1"},{"name":"Hawaiki Cable","cable_id":1733,"id":"hawaiki-cable"},{"name":"APX-East","cable_id":1743,"id":"apx-east"},{"name":"Tasman Global Access (TGA) Cable","cable_id":1750,"id":"tasman-global-access-tga-cable"},{"name":"Polaris","cable_id":1768,"id":"polaris"},{"name":"Trident Subsea Cable","cable_id":1783,"id":"trident-subsea-cable"}],"rfs":"2015"}
