{"latlon":[{"latlon":"0.531064,72.997701"},{"latlon":"2.776766,73.424654"},{"latlon":"4.211922,73.540181"},{"latlon":"6.622467,73.071432"},{"latlon":"5.103230,73.070846"},{"latlon":"3.608113,72.955611"},{"latlon":"1.918466,73.544674"},{"latlon":"0.288779,73.455513"},{"latlon":"-0.606045,73.089205"},{"latlon":"-0.298330,73.426900"},{"latlon":"4.166316,73.499947"}],"cables":[{"cable_id":1868,"name":"Ooredoo Maldives Domestic Submarine Cable System","id":"ooredoo-maldives-domestic-submarine-cable-system"},{"cable_id":1746,"name":"Dhiraagu Cable Network","id":"dhiraagu-cable-network"},{"cable_id":1517,"name":"WARF Submarine Cable","id":"warf-submarine-cable"},{"cable_id":1369,"name":"Dhiraagu-SLT Submarine Cable Network","id":"dhiraagu-slt-submarine-cable-network"}],"landing_points":[{"landing_point_id":16505,"name":"Thinadhoo, Maldives","id":"thinadhoo-maldives"},{"landing_point_id":16506,"name":"Kolhufushi, Maldives","id":"kolhufushi-maldives"},{"landing_point_id":9215,"name":"Hulhumale, Maldives","id":"hulhumale-maldives"},{"landing_point_id":10811,"name":"Kulhudhufushi, Maldives","id":"kulhudhufushi-maldives"},{"landing_point_id":10812,"name":"Eydhafushi, Maldives","id":"eydhafushi-maldives"},{"landing_point_id":10813,"name":"Dhangethi, Maldives","id":"dhangethi-maldives"},{"landing_point_id":10814,"name":"Gan, Maldives","id":"gan-maldives"},{"landing_point_id":10815,"name":"Gahdhoo, Maldives","id":"gahdhoo-maldives"},{"landing_point_id":10816,"name":"Hithadhoo, Maldives","id":"hithadhoo-maldives"},{"landing_point_id":10817,"name":"Fuvahmulah, Maldives","id":"fuvahmulah-maldives"},{"landing_point_id":4251,"name":"Male, Maldives","id":"male-maldives"}],"name":"Maldives"}
