{"landing_points":[{"url":"#/landing-point/seward-alaska-united-states","name":"Seward, Alaska, United States","landing_point_id":5755,"id":"seward-alaska-united-states","latlon":"60.112188,-149.443111"},{"url":"#/landing-point/warrenton-oregon-united-states","name":"Warrenton, Oregon, United States","landing_point_id":6191,"id":"warrenton-oregon-united-states","latlon":"46.165124,-123.923885"}],"rfs":"June 2004","length":"2,485 km","owners":"GCI","cable_id":1348,"notes":null,"url":"http://www.alaskaunited.com","name":"Alaska United West","id":"alaska-united-west"}
