{"landing_points":[{"url":"#/landing-point/eight-mile-rock-bahamas","name":"Eight-Mile Rock, Bahamas","landing_point_id":5783,"id":"eight-mile-rock-bahamas","latlon":"26.539621,-78.802849"},{"url":"#/landing-point/nassau-bahamas","name":"Nassau, Bahamas","landing_point_id":4230,"id":"nassau-bahamas","latlon":"25.067039,-77.340252"},{"url":"#/landing-point/vero-beach-florida-united-states","name":"Vero Beach, Florida, United States","landing_point_id":3813,"id":"vero-beach-florida-united-states","latlon":"27.638388,-80.394255"}],"rfs":"June 1997","length":"470 km","owners":"AT&T,  Telefonica,  Verizon","notes":null,"url":null,"name":"Bahamas 2","id":"bahamas-2","cable_id":1069}
