{"landing_points":[{"latlon":"41.125526,16.866689","url":"#/landing-point/bari-italy","name":"Bari, Italy","id":"bari-italy","landing_point_id":3160},{"latlon":"41.210654,19.499231","url":"#/landing-point/gjirin-e-lalezit-albania","name":"Gjirin e Lalezit, Albania","id":"gjirin-e-lalezit-albania","landing_point_id":10178}],"length":"276 km","rfs":"2013","owners":"UNIFI Communications","url":"http://bin.al","notes":null,"name":"Balkans-Italy Network (BIN)","cable_id":1668,"id":"balkans-italy-network-bin"}
