{"notes":null,"url":null,"length":"1,730 km","cable_id":1290,"landing_points":[{"url":"#/landing-point/basseterre-saint-kitts-and-nevis","landing_point_id":4356,"latlon":"17.298439,-62.731238","name":"Basseterre, Saint Kitts and Nevis","id":"basseterre-saint-kitts-and-nevis"},{"url":"#/landing-point/bridgetown-barbados","landing_point_id":4202,"latlon":"13.098929,-59.613368","name":"Bridgetown, Barbados","id":"bridgetown-barbados"},{"url":"#/landing-point/castries-saint-lucia","landing_point_id":4207,"latlon":"13.994241,-61.006825","name":"Castries, Saint Lucia","id":"castries-saint-lucia"},{"url":"#/landing-point/chaguaramas-trinidad-and-tobago","landing_point_id":8838,"latlon":"10.686137,-61.650819","name":"Chaguaramas, Trinidad and Tobago","id":"chaguaramas-trinidad-and-tobago"},{"url":"#/landing-point/kingstown-saint-vincent-and-the-grenadines","landing_point_id":4219,"latlon":"13.187894,-61.254676","name":"Kingstown, Saint Vincent and the Grenadines","id":"kingstown-saint-vincent-and-the-grenadines"},{"url":"#/landing-point/le-lamentin-martinique","landing_point_id":5905,"latlon":"14.615530,-61.094276","name":"Le Lamentin, Martinique","id":"le-lamentin-martinique"},{"url":"#/landing-point/plymouth-montserrat","landing_point_id":4355,"latlon":"16.706545,-62.215711","name":"Plymouth, Montserrat","id":"plymouth-montserrat"},{"url":"#/landing-point/pointe-a-pitre-guadeloupe","landing_point_id":4906,"latlon":"16.241017,-61.533094","name":"Pointe-a-Pitre, Guadeloupe","id":"pointe-a-pitre-guadeloupe"},{"url":"#/landing-point/roseau-dominica","landing_point_id":4260,"latlon":"15.251760,-61.370741","name":"Roseau, Dominica","id":"roseau-dominica"},{"url":"#/landing-point/saint-maarten-sint-maarten","landing_point_id":10728,"latlon":"18.031056,-63.073718","name":"Saint Maarten, Sint Maarten","id":"saint-maarten-sint-maarten"},{"url":"#/landing-point/st-georges-grenada","landing_point_id":4244,"latlon":"12.187992,-61.711610","name":"St. George's, Grenada","id":"st-georges-grenada"},{"url":"#/landing-point/st-johns-antigua-and-barbuda","landing_point_id":4239,"latlon":"17.051466,-61.857947","name":"St. John’s, Antigua and Barbuda","id":"st-johns-antigua-and-barbuda"},{"url":"#/landing-point/the-valley-anguilla","landing_point_id":4195,"latlon":"18.217384,-63.057214","name":"The Valley, Anguilla","id":"the-valley-anguilla"}],"rfs":"September 1995","name":"Eastern Caribbean Fiber System (ECFS)","owners":"Orange,  Cable & Wireless Communications,  AT&T,  BT,  Verizon,  Sprint,  CANTV,  Guyana Telephone and Telegraph (GT&T),  Codetel,  Columbus Networks","id":"eastern-caribbean-fiber-system-ecfs"}
