{"landing_points":[{"latlon":"18.699000,-70.161838","url":"#/landing-point/haina-dominican-republic","name":"Haina, Dominican Republic","id":"haina-dominican-republic","landing_point_id":10120},{"latlon":"17.949671,-76.716864","url":"#/landing-point/harbour-view-jamaica","name":"Harbour View, Jamaica","id":"harbour-view-jamaica","landing_point_id":9600},{"latlon":"18.414784,-64.597241","url":"#/landing-point/nanny-cay-virgin-islands-u-k-","name":"Nanny Cay, Virgin Islands (U.K.)","id":"nanny-cay-virgin-islands-u-k-","landing_point_id":10121}],"length":"1,750 km","rfs":"February 2011","cable_id":1671,"owners":"C&W Networks","notes":null,"url":"http://www.cwc.com","name":"East-West","id":"east-west"}
