{"landing_points":[{"latlon":"31.071894,29.702539","url":"#/landing-point/abu-talat-egypt","name":"Abu Talat, Egypt","id":"abu-talat-egypt","landing_point_id":9485},{"latlon":"23.679414,58.004373","url":"#/landing-point/barka-oman","name":"Barka, Oman","id":"barka-oman","landing_point_id":8947},{"latlon":"50.828106,-4.544398","url":"#/landing-point/bude-united-kingdom","name":"Bude, United Kingdom","id":"bude-united-kingdom","landing_point_id":4554},{"latlon":"11.594657,43.148039","url":"#/landing-point/djibouti-city-djibouti","name":"Djibouti City, Djibouti","id":"djibouti-city-djibouti","landing_point_id":4177},{"latlon":"25.121671,56.333737","url":"#/landing-point/fujairah-united-arab-emirates","name":"Fujairah, United Arab Emirates","id":"fujairah-united-arab-emirates","landing_point_id":5962},{"latlon":"36.155981,-5.347693","url":"#/landing-point/gibraltar-gibraltar","name":"Gibraltar, Gibraltar","id":"gibraltar-gibraltar","landing_point_id":8948},{"latlon":"21.481246,39.182762","url":"#/landing-point/jeddah-saudi-arabia","name":"Jeddah, Saudi Arabia","id":"jeddah-saudi-arabia","landing_point_id":4361},{"latlon":"43.732570,7.417686","url":"#/landing-point/monaco-monaco","name":"Monaco, Monaco","id":"monaco-monaco","landing_point_id":3255},{"latlon":"19.075779,72.875866","url":"#/landing-point/mumbai-india","name":"Mumbai, India","id":"mumbai-india","landing_point_id":3212},{"latlon":"38.442690,-9.102760","url":"#/landing-point/sesimbra-portugal","name":"Sesimbra, Portugal","id":"sesimbra-portugal","landing_point_id":5934},{"latlon":"32.877350,13.187314","url":"#/landing-point/tripoli-libya","name":"Tripoli, Libya","id":"tripoli-libya","landing_point_id":4271},{"latlon":"29.116662,32.649894","url":"#/landing-point/zafarana-egypt","name":"Zafarana, Egypt","id":"zafarana-egypt","landing_point_id":9486}],"length":"15,000 km","rfs":"February 2011","owners":"AT&T,  airtel (Bharti),  Bharat Sanchar Nigam Ltd. (BSNL),  BT,  Djibouti Telecom,  du,  Gibtelecom,  Libya International Telecommunications Company,  MTN Group,  Omantel,  Portugal Telecom,  Saudi Telecom,  Telecom Egypt,  Telkom South Africa,  Verizon Business,  Vodafone","url":"https://www.europeindiagateway.com","notes":null,"name":"Europe India Gateway (EIG)","cable_id":1580,"id":"europe-india-gateway-eig"}
