{"landing_points":[{"latlon":"17.949741,-76.666652","url":"#/landing-point/bull-bay-jamaica","name":"Bull Bay, Jamaica","id":"bull-bay-jamaica","landing_point_id":7689},{"latlon":"18.542725,-72.343146","url":"#/landing-point/port-au-prince-haiti","name":"Port-au-Prince, Haiti","id":"port-au-prince-haiti","landing_point_id":3878},{"latlon":"19.799366,-70.691232","url":"#/landing-point/puerto-plata-dominican-republic","name":"Puerto Plata, Dominican Republic","id":"puerto-plata-dominican-republic","landing_point_id":5823}],"length":"1,000 km","rfs":"March 2006","owners":"Columbus Networks","url":"http://www.columbus-networks.com","notes":null,"name":"Fibralink","cable_id":1361,"id":"fibralink"}
