{"landing_points":[{"url":"#/landing-point/aberdeen-united-kingdom","name":"Aberdeen, United Kingdom","landing_point_id":3537,"id":"aberdeen-united-kingdom","latlon":"57.153791,-2.106804"},{"url":"#/landing-point/copenhagen-denmark","name":"Copenhagen, Denmark","landing_point_id":3059,"id":"copenhagen-denmark","latlon":"55.676155,12.569312"},{"url":"#/landing-point/draupner-norway","name":"Draupner, Norway","landing_point_id":7648,"id":"draupner-norway","latlon":"58.922540,2.685137"},{"url":"#/landing-point/ekofisk-norway","name":"Ekofisk, Norway","landing_point_id":7649,"id":"ekofisk-norway","latlon":"56.549104,3.210039"},{"url":"#/landing-point/esbjerg-denmark","name":"Esbjerg, Denmark","landing_point_id":3250,"id":"esbjerg-denmark","latlon":"55.465218,8.456912"},{"url":"#/landing-point/krst-norway","name":"Kårstø, Norway","landing_point_id":5923,"id":"krst-norway","latlon":"59.279278,5.524393"},{"url":"#/landing-point/lowestoft-united-kingdom","name":"Lowestoft, United Kingdom","landing_point_id":3084,"id":"lowestoft-united-kingdom","latlon":"52.471371,1.729180"},{"url":"#/landing-point/murdoch-norway","name":"Murdoch, Norway","landing_point_id":7651,"id":"murdoch-norway","latlon":"54.266390,2.333477"},{"url":"#/landing-point/oslo-norway","name":"Oslo, Norway","landing_point_id":3062,"id":"oslo-norway","latlon":"59.912286,10.749977"},{"url":"#/landing-point/ula-norway","name":"Ula, Norway","landing_point_id":7647,"id":"ula-norway","latlon":"57.111115,2.847246"},{"url":"#/landing-point/valhala-norway","name":"Valhala, Norway","landing_point_id":7650,"id":"valhala-norway","latlon":"56.278108,3.395293"}],"rfs":"July 1999","length":"1,751 km","owners":"Tampnet","cable_id":1203,"notes":null,"url":"http://www.tampnet.com/","name":"Tampnet Offshore FOC Network","id":"tampnet-offshore-foc-network"}
